odoo/addons/fieldservice_default_flow/README.rst
odoo/addons/fieldservice_default_flow/__init__.py
odoo/addons/fieldservice_default_flow/__manifest__.py
odoo/addons/fieldservice_default_flow/data/fsm_stage.xml
odoo/addons/fieldservice_default_flow/models/__init__.py
odoo/addons/fieldservice_default_flow/models/fsm_order.py
odoo/addons/fieldservice_default_flow/readme/CONFIGURE.rst
odoo/addons/fieldservice_default_flow/readme/CONTRIBUTORS.rst
odoo/addons/fieldservice_default_flow/readme/CREDITS.rst
odoo/addons/fieldservice_default_flow/readme/DESCRIPTION.rst
odoo/addons/fieldservice_default_flow/readme/ROADMAP.rst
odoo/addons/fieldservice_default_flow/readme/USAGE.rst
odoo/addons/fieldservice_default_flow/static/description/icon.png
odoo/addons/fieldservice_default_flow/static/description/index.html
odoo/addons/fieldservice_default_flow/views/fsm_order.xml
odoo12_addon_fieldservice_default_flow-12.0.1.2.0.99.dev1.dist-info/METADATA
odoo12_addon_fieldservice_default_flow-12.0.1.2.0.99.dev1.dist-info/WHEEL
odoo12_addon_fieldservice_default_flow-12.0.1.2.0.99.dev1.dist-info/top_level.txt
odoo12_addon_fieldservice_default_flow-12.0.1.2.0.99.dev1.dist-info/RECORD
